{"aR":{"$":0,"a":{"bT":{"$":0,"a":1211397742},"bd":{"$":0},"b6":3530670207,"cd":0}},"c_":{"$":0,"a":{"bT":{"$":0,"a":1211397742},"bd":{"$":0},"b6":3530670207,"cd":0}},"ew":{"$":1},"b0":{"$":1},"I":{"$":-1,"a":1,"b":"src/Util.elm","c":{"bT":3931762650,"bd":{"$":0},"b6":3530670207,"c7":false,"cd":0},"d":{"$":-1,"a":1,"b":"src/NoUnsortedRecords.elm","c":{"bT":1867145513,"bd":{"$":0},"b6":3530670207,"c7":false,"cd":0},"d":{"$":-1,"a":1,"b":"src/NoUnsortedLetDeclarations.elm","c":{"bT":4251273345,"bd":{"$":0},"b6":3530670207,"c7":false,"cd":0},"d":{"$":-1,"a":0,"b":"src/NoUnsortedCases.elm","c":{"bT":3284525811,"bd":{"$":0},"b6":3530670207,"c7":false,"cd":0},"d":{"$":-2},"e":{"$":-2}},"e":{"$":-2}},"e":{"$":-1,"a":1,"b":"src/NoUnsortedTopLevelDeclarations.elm","c":{"bT":2600031148,"bd":{"$":0},"b6":3530670207,"c7":false,"cd":0},"d":{"$":-2},"e":{"$":-2}}},"e":{"$":-1,"a":1,"b":"tests/NoUnsortedRecordsTest.elm","c":{"bT":2575785783,"bd":{"$":0},"b6":3530670207,"c7":false,"cd":0},"d":{"$":-1,"a":1,"b":"tests/NoUnsortedLetDeclarationsTest.elm","c":{"bT":1983685284,"bd":{"$":0},"b6":3530670207,"c7":false,"cd":0},"d":{"$":-1,"a":0,"b":"tests/NoUnsortedCasesTest.elm","c":{"bT":1133119512,"bd":{"$":0},"b6":3530670207,"c7":false,"cd":0},"d":{"$":-2},"e":{"$":-2}},"e":{"$":-2}},"e":{"$":-1,"a":1,"b":"tests/NoUnsortedTopLevelDeclarationsTest.elm","c":{"bT":3504192216,"bd":{"$":0},"b6":3530670207,"c7":false,"cd":0},"d":{"$":-2},"e":{"$":-2}}}},"dZ":{"$":0,"a":{"bT":{"$":0,"a":3715779789},"bd":{"$":0},"b6":3530670207,"cd":0}}}
